{"id": "a0cd028d-9f13-492d-aa64-43ccd3d7dadb", "obj_type": "сделка", "name": "API3 #4", "data": {"emoji_entry": {"number": 4, "symbol": "API3", "entry_price": 0.2992, "entry_date": "2025-12-18", "entry_time": 129, "volume": 0.32, "pnl_percent": 78.54, "pnl_usdt": 0.25, "result": "🟢", "status": "green"}, "leverage": 10, "emoji_upd": {"current_price": 0.3427, "entry_time": 129, "pnl_percent": 14.54, "pnl_usdt": 0.04}, "ohlc": {"current": {"high": 0.5086, "low": 0.2498, "body": 0.0435, "body_pct": 14.5388, "upper_wick": 0.1659, "lower_wick": 0.0494, "pct": 14.5388, "pct_x": 145.39}, "max": {"price": 0.5086, "pct": 69.99, "pct_x": 699.87, "volatility": 0.2588}, "min": {"price": 0.2498, "pct": -16.51, "pct_x": -165.11, "volatility": 0.2588}}, "stats": {"dn": 1, "dp": 1, "da": 0}, "chart_updated": "2026-04-26 18:26", "entry_at": "2025-12-18"}, "created_at": "2026-04-24 22:40:53.504498", "updated_at": "2026-04-26 18:26:16.907890"}